<?xml version="1.0"?>
<TriggernometryExport Version="1">
  <ExportedFolder Id="7ac0b969-d7af-4a84-8851-c232b596b500" Name="队伍监控 by Souma" Enabled="true">
    <Folders>
      <Folder Id="56fa4a3b-5c94-460f-9ed2-1d48ae31ae2c" Name="*设置" Enabled="true">
        <Folders />
        <Triggers>
          <Trigger Enabled="true" Name="聊天频道" Id="96d5046f-9d32-4e72-ad30-1fb6da42190d" RegularExpression="^." PeriodRefire="Deny" RefirePeriodExpression="86400000" EditAutofire="True">
            <Actions>
              <Action OrderNumber="1" VariableOp="SetString" VariableName="_AT_技能判定_发送频道" VariableExpression="e" TextAuraFontSize="9" TextAuraFontName="宋体" ActionType="Variable">
                <Condition Enabled="false" Grouping="Or" />
                <Conditions />
              </Action>
              <Action OrderNumber="2" VariableOp="SetString" VariableName="_AT_伊甸平A职能_发送频道" VariableExpression="e" TextAuraFontSize="9" TextAuraFontName="宋体" ActionType="Variable">
                <Condition Enabled="false" Grouping="Or" />
                <Conditions />
              </Action>
              <Action OrderNumber="3" VariableOp="SetString" VariableName="_AT_即刻_发送频道" VariableExpression="e" TextAuraFontSize="9" TextAuraFontName="宋体" ActionType="Variable">
                <Condition Enabled="false" Grouping="Or" />
                <Conditions />
              </Action>
            </Actions>
            <Condition Enabled="false" Grouping="Or" />
          </Trigger>
          <Trigger Enabled="true" Name="技能ID" Id="06d8b85e-22d9-4349-b9d1-64a68c0bbebd" RegularExpression="^." PeriodRefire="Deny" RefirePeriodExpression="86400000" EditAutofire="True">
            <Actions>
              <Action OrderNumber="1" LogLevel="-1" TextAuraFontSize="9" TextAuraFontName="宋体" TriggerId="0caa2d29-6cbf-4acd-b6f4-07e82f1e328e" TriggerForce="regexp" ActionType="Trigger">
                <Condition Enabled="false" Grouping="Or" />
              </Action>
              <Action OrderNumber="2" ListVariableExpressionType="Numeric" ListVariableName="AT_监控ID" TextAuraFontSize="8.25" TextAuraFontName="Microsoft Sans Serif" ActionType="ListVariable" Asynchronous="False">
                <Condition Enabled="false" Grouping="Or" />
              </Action>
              <Action OrderNumber="3" ListVariableOp="Push" ListVariableName="AT_监控ID" ListVariableExpression="44F8" TextAuraFontSize="8.25" TextAuraFontName="Microsoft Sans Serif" ActionType="ListVariable" Asynchronous="False">
                <Condition Enabled="false" Grouping="Or" />
              </Action>
              <Action OrderNumber="4" ListVariableOp="Push" ListVariableName="AT_监控ID" ListVariableExpression="3D8B" TextAuraFontSize="8.25" TextAuraFontName="Microsoft Sans Serif" ActionType="ListVariable" Asynchronous="False">
                <Condition Enabled="false" Grouping="Or" />
              </Action>
              <Action OrderNumber="5" ListVariableOp="Push" ListVariableName="AT_监控ID" ListVariableExpression="3D7F" TextAuraFontSize="8.25" TextAuraFontName="Microsoft Sans Serif" ActionType="ListVariable" Asynchronous="False">
                <Condition Enabled="false" Grouping="Or" />
              </Action>
              <Action OrderNumber="6" ListVariableOp="Push" ListVariableName="AT_监控ID" ListVariableExpression="3D8F" TextAuraFontSize="8.25" TextAuraFontName="Microsoft Sans Serif" ActionType="ListVariable" Asynchronous="False">
                <Condition Enabled="false" Grouping="Or" />
              </Action>
              <Action OrderNumber="7" ListVariableOp="Push" ListVariableName="AT_监控ID" ListVariableExpression="44F4" TextAuraFontSize="8.25" TextAuraFontName="Microsoft Sans Serif" ActionType="ListVariable" Asynchronous="False">
                <Condition Enabled="false" Grouping="Or" />
              </Action>
              <Action OrderNumber="8" ListVariableOp="Push" ListVariableName="AT_监控ID" ListVariableExpression="3D70" TextAuraFontSize="8.25" TextAuraFontName="Microsoft Sans Serif" ActionType="ListVariable" Asynchronous="False">
                <Condition Enabled="false" Grouping="Or" />
              </Action>
              <Action OrderNumber="9" ListVariableOp="Push" ListVariableName="AT_监控ID" ListVariableExpression="3E71" TextAuraFontSize="8.25" TextAuraFontName="Microsoft Sans Serif" ActionType="ListVariable" Asynchronous="False">
                <Condition Enabled="false" Grouping="Or" />
              </Action>
              <Action OrderNumber="10" ListVariableOp="Push" ListVariableName="AT_监控ID" ListVariableExpression="3E59" TextAuraFontSize="8.25" TextAuraFontName="Microsoft Sans Serif" ActionType="ListVariable" Asynchronous="False">
                <Condition Enabled="false" Grouping="Or" />
              </Action>
              <Action OrderNumber="11" ListVariableOp="Push" ListVariableName="AT_监控ID" ListVariableExpression="3E63" TextAuraFontSize="8.25" TextAuraFontName="Microsoft Sans Serif" ActionType="ListVariable" Asynchronous="False">
                <Condition Enabled="false" Grouping="Or" />
              </Action>
              <Action OrderNumber="12" ListVariableOp="Push" ListVariableName="AT_监控ID" ListVariableExpression="3E6F" TextAuraFontSize="8.25" TextAuraFontName="Microsoft Sans Serif" ActionType="ListVariable" Asynchronous="False">
                <Condition Enabled="false" Grouping="Or" />
              </Action>
              <Action OrderNumber="13" ListVariableOp="Push" ListVariableName="AT_监控ID" ListVariableExpression="3FF3" TextAuraFontSize="8.25" TextAuraFontName="Microsoft Sans Serif" ActionType="ListVariable" Asynchronous="False">
                <Condition Enabled="false" Grouping="Or" />
              </Action>
              <Action OrderNumber="14" ListVariableOp="Push" ListVariableName="AT_监控ID" ListVariableExpression="3FDC" TextAuraFontSize="8.25" TextAuraFontName="Microsoft Sans Serif" ActionType="ListVariable" Asynchronous="False">
                <Condition Enabled="false" Grouping="Or" />
              </Action>
              <Action OrderNumber="15" ListVariableOp="Push" ListVariableName="AT_监控ID" ListVariableExpression="3FDE" TextAuraFontSize="8.25" TextAuraFontName="Microsoft Sans Serif" ActionType="ListVariable" Asynchronous="False">
                <Condition Enabled="false" Grouping="Or" />
              </Action>
              <Action OrderNumber="16" ListVariableOp="Push" ListVariableName="AT_监控ID" ListVariableExpression="400C" TextAuraFontSize="8.25" TextAuraFontName="Microsoft Sans Serif" ActionType="ListVariable" Asynchronous="False">
                <Condition Enabled="false" Grouping="Or" />
              </Action>
              <Action OrderNumber="17" ListVariableOp="Push" ListVariableName="AT_监控ID" ListVariableExpression="400B" TextAuraFontSize="8.25" TextAuraFontName="Microsoft Sans Serif" ActionType="ListVariable" Asynchronous="False">
                <Condition Enabled="false" Grouping="Or" />
              </Action>
              <Action OrderNumber="18" ListVariableOp="Push" ListVariableName="AT_监控ID" ListVariableExpression="3FF2" TextAuraFontSize="8.25" TextAuraFontName="Microsoft Sans Serif" ActionType="ListVariable" Asynchronous="False">
                <Condition Enabled="false" Grouping="Or" />
              </Action>
              <Action OrderNumber="19" ListVariableOp="Push" ListVariableName="AT_监控ID" ListVariableExpression="4124" TextAuraFontSize="8.25" TextAuraFontName="Microsoft Sans Serif" ActionType="ListVariable" Asynchronous="False">
                <Condition Enabled="false" Grouping="Or" />
              </Action>
              <Action OrderNumber="20" ListVariableOp="Push" ListVariableName="AT_监控ID" ListVariableExpression="4139" TextAuraFontSize="8.25" TextAuraFontName="Microsoft Sans Serif" ActionType="ListVariable" Asynchronous="False">
                <Condition Enabled="false" Grouping="Or" />
              </Action>
              <Action OrderNumber="21" ListVariableOp="Push" ListVariableName="AT_监控ID" ListVariableExpression="4114" TextAuraFontSize="8.25" TextAuraFontName="Microsoft Sans Serif" ActionType="ListVariable" Asynchronous="False">
                <Condition Enabled="false" Grouping="Or" />
              </Action>
              <Action OrderNumber="22" ListVariableOp="Push" ListVariableName="AT_监控ID" ListVariableExpression="412A" TextAuraFontSize="8.25" TextAuraFontName="Microsoft Sans Serif" ActionType="ListVariable" Asynchronous="False">
                <Condition Enabled="false" Grouping="Or" />
              </Action>
              <Action OrderNumber="23" ListVariableOp="Push" ListVariableName="AT_监控ID" ListVariableExpression="4BB5" TextAuraFontSize="8.25" TextAuraFontName="Microsoft Sans Serif" ActionType="ListVariable" Asynchronous="False">
                <Condition Enabled="false" Grouping="Or" />
              </Action>
              <Action OrderNumber="24" ListVariableOp="Push" ListVariableName="AT_监控ID" ListVariableExpression="4BB6" TextAuraFontSize="8.25" TextAuraFontName="Microsoft Sans Serif" ActionType="ListVariable" Asynchronous="False">
                <Condition Enabled="false" Grouping="Or" />
              </Action>
              <Action OrderNumber="25" ListVariableOp="Push" ListVariableName="AT_监控ID" ListVariableExpression="4BF7" TextAuraFontSize="8.25" TextAuraFontName="Microsoft Sans Serif" ActionType="ListVariable" Asynchronous="False">
                <Condition Enabled="false" Grouping="Or" />
              </Action>
              <Action OrderNumber="26" ListVariableOp="Push" ListVariableName="AT_监控ID" ListVariableExpression="4C14" TextAuraFontSize="8.25" TextAuraFontName="Microsoft Sans Serif" ActionType="ListVariable" Asynchronous="False">
                <Condition Enabled="false" Grouping="Or" />
              </Action>
              <Action OrderNumber="27" ListVariableOp="Push" ListVariableName="AT_监控ID" ListVariableExpression="4C00" TextAuraFontSize="8.25" TextAuraFontName="Microsoft Sans Serif" ActionType="ListVariable" Asynchronous="False">
                <Condition Enabled="false" Grouping="Or" />
              </Action>
              <Action OrderNumber="28" ListVariableOp="Push" ListVariableName="AT_监控ID" ListVariableExpression="4BF9" TextAuraFontSize="8.25" TextAuraFontName="Microsoft Sans Serif" ActionType="ListVariable" Asynchronous="False">
                <Condition Enabled="false" Grouping="Or" />
              </Action>
              <Action OrderNumber="29" ListVariableOp="Push" ListVariableName="AT_监控ID" ListVariableExpression="4C6D" TextAuraFontSize="8.25" TextAuraFontName="Microsoft Sans Serif" ActionType="ListVariable" Asynchronous="False">
                <Condition Enabled="false" Grouping="Or" />
              </Action>
              <Action OrderNumber="30" ListVariableOp="Push" ListVariableName="AT_监控ID" ListVariableExpression="4C75" TextAuraFontSize="8.25" TextAuraFontName="Microsoft Sans Serif" ActionType="ListVariable" Asynchronous="False">
                <Condition Enabled="false" Grouping="Or" />
              </Action>
              <Action OrderNumber="31" ListVariableOp="Push" ListVariableName="AT_监控ID" ListVariableExpression="4C7E" TextAuraFontSize="8.25" TextAuraFontName="Microsoft Sans Serif" ActionType="ListVariable" Asynchronous="False">
                <Condition Enabled="false" Grouping="Or" />
              </Action>
              <Action OrderNumber="32" ListVariableOp="Push" ListVariableName="AT_监控ID" ListVariableExpression="4C8A" TextAuraFontSize="8.25" TextAuraFontName="Microsoft Sans Serif" ActionType="ListVariable" Asynchronous="False">
                <Condition Enabled="false" Grouping="Or" />
              </Action>
              <Action OrderNumber="33" ListVariableOp="Push" ListVariableName="AT_监控ID" ListVariableExpression="4E56" TextAuraFontSize="8.25" TextAuraFontName="Microsoft Sans Serif" ActionType="ListVariable" Asynchronous="False">
                <Condition Enabled="false" Grouping="Or" />
              </Action>
              <Action OrderNumber="34" ListVariableOp="Push" ListVariableName="AT_监控ID" ListVariableExpression="4DCC" TextAuraFontSize="8.25" TextAuraFontName="Microsoft Sans Serif" ActionType="ListVariable" Asynchronous="False">
                <Condition Enabled="false" Grouping="Or" />
              </Action>
              <Action OrderNumber="35" ListVariableOp="Push" ListVariableName="AT_监控ID" ListVariableExpression="4D80" TextAuraFontSize="8.25" TextAuraFontName="Microsoft Sans Serif" ActionType="ListVariable" Asynchronous="False">
                <Condition Enabled="false" Grouping="Or" />
              </Action>
              <Action OrderNumber="36" ListVariableOp="Push" ListVariableName="AT_监控ID" ListVariableExpression="4D64" TextAuraFontSize="8.25" TextAuraFontName="Microsoft Sans Serif" ActionType="ListVariable" Asynchronous="False">
                <Condition Enabled="false" Grouping="Or" />
              </Action>
              <Action OrderNumber="37" ListVariableOp="Push" ListVariableName="AT_监控ID" ListVariableExpression="4D98" TextAuraFontSize="8.25" TextAuraFontName="Microsoft Sans Serif" ActionType="ListVariable" Asynchronous="False">
                <Condition Enabled="false" Grouping="Or" />
              </Action>
              <Action OrderNumber="38" ListVariableOp="Push" ListVariableName="AT_监控ID" ListVariableExpression="4D7B" TextAuraFontSize="8.25" TextAuraFontName="Microsoft Sans Serif" ActionType="ListVariable" Asynchronous="False">
                <Condition Enabled="false" Grouping="Or" />
              </Action>
              <Action OrderNumber="39" ListVariableOp="Push" ListVariableName="AT_监控ID" ListVariableExpression="4D82" TextAuraFontSize="8.25" TextAuraFontName="Microsoft Sans Serif" ActionType="ListVariable" Asynchronous="False">
                <Condition Enabled="false" Grouping="Or" />
              </Action>
              <Action OrderNumber="40" ListVariableOp="Push" ListVariableName="AT_监控ID" ListVariableExpression="4D83" TextAuraFontSize="8.25" TextAuraFontName="Microsoft Sans Serif" ActionType="ListVariable" Asynchronous="False">
                <Condition Enabled="false" Grouping="Or" />
              </Action>
              <Action OrderNumber="41" ListVariableOp="Push" ListVariableName="AT_监控ID" ListVariableExpression="4D6C" TextAuraFontSize="8.25" TextAuraFontName="Microsoft Sans Serif" ActionType="ListVariable" Asynchronous="False">
                <Condition Enabled="false" Grouping="Or" />
              </Action>
              <Action OrderNumber="42" ListVariableOp="Push" ListVariableName="AT_监控ID" ListVariableExpression="4D9E" TextAuraFontSize="8.25" TextAuraFontName="Microsoft Sans Serif" ActionType="ListVariable" Asynchronous="False">
                <Condition Enabled="false" Grouping="Or" />
              </Action>
              <Action OrderNumber="43" ListVariableOp="Push" ListVariableName="AT_监控ID" ListVariableExpression="4D73" TextAuraFontSize="8.25" TextAuraFontName="Microsoft Sans Serif" ActionType="ListVariable" Asynchronous="False">
                <Condition Enabled="false" Grouping="Or" />
              </Action>
              <Action OrderNumber="44" ListVariableOp="Push" ListVariableName="AT_监控ID" ListVariableExpression="4DA1" TextAuraFontSize="8.25" TextAuraFontName="Microsoft Sans Serif" ActionType="ListVariable" Asynchronous="False">
                <Condition Enabled="false" Grouping="Or" />
              </Action>
              <Action OrderNumber="45" ListVariableOp="Push" ListVariableName="AT_监控ID" ListVariableExpression="4DA8" TextAuraFontSize="8.25" TextAuraFontName="Microsoft Sans Serif" ActionType="ListVariable" Asynchronous="False">
                <Condition Enabled="false" Grouping="Or" />
              </Action>
              <Action OrderNumber="46" ListVariableOp="Push" ListVariableName="AT_监控ID" ListVariableExpression="4DA9" TextAuraFontSize="8.25" TextAuraFontName="Microsoft Sans Serif" ActionType="ListVariable" Asynchronous="False">
                <Condition Enabled="false" Grouping="Or" />
              </Action>
              <Action OrderNumber="47" ListVariableOp="Push" ListVariableName="AT_监控ID" ListVariableExpression="4D7C" TextAuraFontSize="8.25" TextAuraFontName="Microsoft Sans Serif" ActionType="ListVariable" Asynchronous="False">
                <Condition Enabled="false" Grouping="Or" />
              </Action>
              <Action OrderNumber="48" ListVariableOp="Push" ListVariableName="AT_监控ID" ListVariableExpression="4DBD" TextAuraFontSize="8.25" TextAuraFontName="Microsoft Sans Serif" ActionType="ListVariable" Asynchronous="False">
                <Condition Enabled="false" Grouping="Or" />
              </Action>
              <Action OrderNumber="49" ListVariableOp="Push" ListVariableName="AT_监控ID" ListVariableExpression="4DBB" TextAuraFontSize="8.25" TextAuraFontName="Microsoft Sans Serif" ActionType="ListVariable" Asynchronous="False">
                <Condition Enabled="false" Grouping="Or" />
              </Action>
              <Action OrderNumber="50" ListVariableOp="Push" ListVariableName="AT_监控ID" ListVariableExpression="4DC7" TextAuraFontSize="8.25" TextAuraFontName="Microsoft Sans Serif" ActionType="ListVariable" Asynchronous="False">
                <Condition Enabled="false" Grouping="Or" />
              </Action>
              <Action OrderNumber="51" ListVariableOp="Push" ListVariableName="AT_监控ID" ListVariableExpression="47A7" TextAuraFontSize="8.25" TextAuraFontName="Microsoft Sans Serif" ActionType="ListVariable" Asynchronous="False">
                <Condition Enabled="false" Grouping="Or" />
              </Action>
              <Action OrderNumber="52" ListVariableOp="Push" ListVariableName="AT_监控ID" ListVariableExpression="47A8" TextAuraFontSize="8.25" TextAuraFontName="Microsoft Sans Serif" ActionType="ListVariable" Asynchronous="False">
                <Condition Enabled="false" Grouping="Or" />
              </Action>
              <Action OrderNumber="53" ListVariableOp="Push" ListVariableName="AT_监控ID" ListVariableExpression="47A9" TextAuraFontSize="8.25" TextAuraFontName="Microsoft Sans Serif" ActionType="ListVariable" Asynchronous="False">
                <Condition Enabled="false" Grouping="Or" />
              </Action>
              <Action OrderNumber="54" ListVariableOp="Push" ListVariableName="AT_监控ID" ListVariableExpression="478A" TextAuraFontSize="8.25" TextAuraFontName="Microsoft Sans Serif" ActionType="ListVariable" Asynchronous="False">
                <Condition Enabled="false" Grouping="Or" />
              </Action>
              <Action OrderNumber="55" ListVariableOp="Push" ListVariableName="AT_监控ID" ListVariableExpression="47E4" TextAuraFontSize="8.25" TextAuraFontName="Microsoft Sans Serif" ActionType="ListVariable" Asynchronous="False">
                <Condition Enabled="false" Grouping="Or" />
              </Action>
              <Action OrderNumber="56" ListVariableOp="Push" ListVariableName="AT_监控ID" ListVariableExpression="47AA" TextAuraFontSize="8.25" TextAuraFontName="Microsoft Sans Serif" ActionType="ListVariable" Asynchronous="False">
                <Condition Enabled="false" Grouping="Or" />
              </Action>
              <Action OrderNumber="57" ListVariableOp="Push" ListVariableName="AT_监控ID" ListVariableExpression="47B8" TextAuraFontSize="8.25" TextAuraFontName="Microsoft Sans Serif" ActionType="ListVariable" Asynchronous="False">
                <Condition Enabled="false" Grouping="Or" />
              </Action>
              <Action OrderNumber="58" ListVariableOp="Push" ListVariableName="AT_监控ID" ListVariableExpression="47BC" TextAuraFontSize="8.25" TextAuraFontName="Microsoft Sans Serif" ActionType="ListVariable" Asynchronous="False">
                <Condition Enabled="false" Grouping="Or" />
              </Action>
              <Action OrderNumber="59" ListVariableOp="Push" ListVariableName="AT_监控ID" ListVariableExpression="2B42" TextAuraFontSize="8.25" TextAuraFontName="Microsoft Sans Serif" ActionType="ListVariable" Asynchronous="False">
                <Condition Enabled="false" Grouping="Or" />
              </Action>
              <Action OrderNumber="60" ListVariableOp="Push" ListVariableName="AT_监控ID" ListVariableExpression="2B54" TextAuraFontSize="8.25" TextAuraFontName="Microsoft Sans Serif" ActionType="ListVariable" Asynchronous="False">
                <Condition Enabled="false" Grouping="Or" />
              </Action>
              <Action OrderNumber="61" ListVariableOp="Push" ListVariableName="AT_监控ID" ListVariableExpression="2B55" TextAuraFontSize="8.25" TextAuraFontName="Microsoft Sans Serif" ActionType="ListVariable" Asynchronous="False">
                <Condition Enabled="false" Grouping="Or" />
              </Action>
              <Action OrderNumber="62" ListVariableOp="Push" ListVariableName="AT_监控ID" ListVariableExpression="2B47" TextAuraFontSize="8.25" TextAuraFontName="Microsoft Sans Serif" ActionType="ListVariable" Asynchronous="False">
                <Condition Enabled="false" Grouping="Or" />
              </Action>
            </Actions>
            <Condition Enabled="false" Grouping="Or" />
          </Trigger>
        </Triggers>
      </Folder>
      <Folder Id="ac5c5fa0-cf8b-4703-8900-2cdd5fe392ec" Name="Main" Enabled="true">
        <Folders>
          <Folder Id="b68b01c4-9a9e-448e-8972-d36420c0d5c0" Name="减伤判定" Enabled="true">
            <Folders>
              <Folder Id="0490bf67-791e-4694-ae8c-7c7ba72d9e5c" Name="获取减伤" Enabled="true">
                <Folders />
                <Triggers>
                  <Trigger Enabled="true" Name="昏乱减伤" Id="69cace14-c950-4e7a-a2b8-14b42df2af9b" RegularExpression="^.{15}1[56]:.{8}:(?&lt;CasterName&gt;[^:]+?):1D88:(?&lt;AbilityName&gt;[^:]+?):.{8}:(?&lt;TargetName&gt;[^:]+?):">
                    <Actions>
                      <Action OrderNumber="-1" VariableOp="SetString" VariableName="减伤_昏乱_${TargetName}" VariableExpression="昏乱 " TextAuraFontSize="9" TextAuraFontName="宋体" ActionType="Variable">
                        <Condition Enabled="false" Grouping="Or" />
                      </Action>
                      <Action OrderNumber="2" VariableName="减伤_昏乱_${TargetName}" VariableExpression="1" TextAuraFontSize="9" TextAuraFontName="宋体" ActionType="Variable" ExecutionDelayExpression="10*1000">
                        <Condition Enabled="false" Grouping="Or" />
                      </Action>
                    </Actions>
                    <Condition Enabled="true" Grouping="Or">
                      <ConditionSingle Enabled="true" ExpressionL="${_ffxivparty[${CasterName}].inparty}" ExpressionTypeL="Numeric" ExpressionR="1" ExpressionTypeR="Numeric" ConditionType="StringEqualNocase" />
                    </Condition>
                  </Trigger>
                  <Trigger Enabled="true" Name="雪仇减伤" Id="62d179db-0ba1-47c2-8dd5-d09fd6982585" RegularExpression="^.{15}1[56]:.{8}:(?&lt;CasterName&gt;[^:]+?):1D6F:.+?:.{8}:(?&lt;TargetName&gt;[^:]+?):">
                    <Actions>
                      <Action OrderNumber="-1" VariableOp="SetString" VariableName="减伤_雪仇_${TargetName}" VariableExpression="雪仇 " TextAuraFontSize="9" TextAuraFontName="宋体" ActionType="Variable">
                        <Condition Enabled="false" Grouping="Or" />
                      </Action>
                      <Action OrderNumber="2" VariableName="减伤_雪仇_${TargetName}" VariableExpression="1" TextAuraFontSize="9" TextAuraFontName="宋体" ActionType="Variable" ExecutionDelayExpression="10*1000">
                        <Condition Enabled="false" Grouping="Or" />
                      </Action>
                    </Actions>
                    <Condition Enabled="true" Grouping="Or">
                      <ConditionSingle Enabled="true" ExpressionL="${_ffxivparty[${CasterName}].inparty}" ExpressionTypeL="Numeric" ExpressionR="1" ExpressionTypeR="Numeric" ConditionType="StringEqualNocase" />
                    </Condition>
                  </Trigger>
                  <Trigger Enabled="true" Name="命运之轮减伤" Id="85176f5d-a3b7-4ba6-9ba9-b7af8f5d63f3" RegularExpression="^.{15}1A:.{8}:(?&lt;name&gt;.+?) gains the effect of (命运之轮|Collective Unconscious|運命の輪：効果) from .+? for (?&lt;time&gt;(?:4|5|19|20)\.[0-9]{2}) Seconds\.$" PrevActions="Interrupt">
                    <Actions>
                      <Action OrderNumber="1" VariableOp="SetString" VariableName="减伤_命运之轮" VariableExpression="命运之轮 " TextAuraFontSize="9" TextAuraFontName="宋体" ActionType="Variable">
                        <Condition Enabled="false" Grouping="Or" />
                      </Action>
                      <Action OrderNumber="2" VariableName="减伤_命运之轮" TextAuraFontSize="9" TextAuraFontName="宋体" ActionType="Variable" ExecutionDelayExpression="${time}*1000">
                        <Condition Enabled="false" Grouping="Or" />
                      </Action>
                    </Actions>
                    <Condition Enabled="true" Grouping="Or">
                      <ConditionSingle Enabled="true" ExpressionL="${name}" ExpressionTypeL="String" ExpressionR="${_ffxivplayer}" ExpressionTypeR="String" ConditionType="StringEqualNocase" />
                    </Condition>
                  </Trigger>
                  <Trigger Enabled="true" Name="野战治疗阵减伤" Id="db5a0137-d9a7-4b0f-8ea0-8d397d6a0290" RegularExpression="^.{15}1A:.{8}:(?&lt;name&gt;.+?) gains the effect of (野战治疗阵|Sacred Soil|野戦治療の陣：効果) from .+? for (?&lt;time&gt;[45]\.[0-9]{2}) Seconds\." PrevActions="Interrupt">
                    <Actions>
                      <Action OrderNumber="1" VariableOp="SetString" VariableName="减伤_野战治疗阵" VariableExpression="野战 " TextAuraFontSize="9" TextAuraFontName="宋体" ActionType="Variable">
                        <Condition Enabled="false" Grouping="Or" />
                      </Action>
                      <Action OrderNumber="2" VariableName="减伤_野战治疗阵" TextAuraFontSize="9" TextAuraFontName="宋体" ActionType="Variable" ExecutionDelayExpression="${time}*1000">
                        <Condition Enabled="false" Grouping="Or" />
                      </Action>
                    </Actions>
                    <Condition Enabled="true" Grouping="Or">
                      <ConditionSingle Enabled="true" ExpressionL="${name}" ExpressionTypeL="String" ExpressionR="${_ffxivplayer}" ExpressionTypeR="String" ConditionType="StringEqualNocase" />
                    </Condition>
                  </Trigger>
                  <Trigger Enabled="true" Name="牵制减伤" Id="3358bc19-5afa-485f-9d45-281880768386" RegularExpression="^.{15}1[56]:.{8}:(?&lt;CasterName&gt;[^:]+?):1D7D:(?&lt;AbilityName&gt;[^:]+?):.{8}:(?&lt;TargetName&gt;[^:]+?):">
                    <Actions>
                      <Action OrderNumber="-1" VariableOp="SetString" VariableName="减伤_牵制_${TargetName}" VariableExpression="牵制 " TextAuraFontSize="9" TextAuraFontName="宋体" ActionType="Variable">
                        <Condition Enabled="false" Grouping="Or" />
                      </Action>
                      <Action OrderNumber="2" VariableName="减伤_牵制_${TargetName}" VariableExpression="1" TextAuraFontSize="9" TextAuraFontName="宋体" ActionType="Variable" ExecutionDelayExpression="10*1000">
                        <Condition Enabled="false" Grouping="Or" />
                      </Action>
                    </Actions>
                    <Condition Enabled="true" Grouping="Or">
                      <ConditionSingle Enabled="true" ExpressionL="${_ffxivparty[${CasterName}].inparty}" ExpressionTypeL="Numeric" ExpressionR="1" ExpressionTypeR="Numeric" ConditionType="StringEqualNocase" />
                    </Condition>
                  </Trigger>
                  <Trigger Enabled="true" Name="*清除变量" Id="11e1af81-a8c3-4d6b-899f-ae1d4241f0f0" RegularExpression="^.{14} 21:.{8}:400000(03|1[026]):00:00:00:00">
                    <Actions>
                      <Action OrderNumber="1" VariableOp="UnsetRegex" VariableName="^(?:减伤|减伤)_.+" TextAuraFontSize="9" TextAuraFontName="宋体" ActionType="Variable">
                        <Condition Enabled="false" Grouping="Or" />
                      </Action>
                    </Actions>
                    <Condition Enabled="false" Grouping="Or" />
                  </Trigger>
                  <Trigger Enabled="true" Name="异想的幻光减伤" Id="a776040a-9d2d-4ff2-8772-cd614b90168d" RegularExpression="^.{15}1A:.{8}:(?&lt;name&gt;.+?) gains the effect of (..的幻光|Fey Illumination|フェイイルミネーション|Seraphic Illumination|セラフィックイルミネーション) from .+? for (?&lt;time&gt;[\d\.]+) Seconds\." PrevActions="Interrupt">
                    <Actions>
                      <Action OrderNumber="1" VariableOp="SetString" VariableName="减伤_异想的幻光" VariableExpression="幻光 " TextAuraFontSize="9" TextAuraFontName="宋体" ActionType="Variable">
                        <Condition Enabled="false" Grouping="Or" />
                      </Action>
                      <Action OrderNumber="2" VariableName="减伤_异想的幻光" TextAuraFontSize="9" TextAuraFontName="宋体" ActionType="Variable" ExecutionDelayExpression="${time}*1000">
                        <Condition Enabled="false" Grouping="Or" />
                      </Action>
                    </Actions>
                    <Condition Enabled="true" Grouping="Or">
                      <ConditionSingle Enabled="true" ExpressionL="${name}" ExpressionTypeL="String" ExpressionR="${_ffxivplayer}" ExpressionTypeR="String" ConditionType="StringEqualNocase" />
                    </Condition>
                  </Trigger>
                  <Trigger Enabled="true" Name="buff" Id="b8730a44-70cb-49c4-b2e9-f97653ca6028" RegularExpression="^.{14} 1[AE]:.{8}:(?&lt;name&gt;.+?) (?&lt;type&gt;gains|loses) the effect of (?&lt;skill&gt;摆脱|炽天的幕帘|鼓舞|黑夜领域|圣光幕帘|天星冲日（夜）|暗黑布道|策动|防守之桑巴|光之心|行吟|节制|武装) from " PrevActions="Interrupt">
                    <Actions>
                      <Action OrderNumber="1" VariableOp="SetString" VariableName="减伤_${skill}" VariableExpression="${skill} " TextAuraFontSize="9" TextAuraFontName="宋体" ActionType="Variable">
                        <Condition Enabled="true" Grouping="Or">
                          <ConditionSingle Enabled="true" ExpressionL="${type}" ExpressionTypeL="String" ExpressionR="gains" ExpressionTypeR="String" ConditionType="StringEqualNocase" />
                        </Condition>
                      </Action>
                      <Action OrderNumber="2" VariableName="减伤_${skill}" VariableExpression="${skill} " TextAuraFontSize="9" TextAuraFontName="宋体" ActionType="Variable" ExecutionDelayExpression="10">
                        <Condition Enabled="true" Grouping="Or">
                          <ConditionSingle Enabled="true" ExpressionL="${type}" ExpressionTypeL="String" ExpressionR="loses" ExpressionTypeR="String" ConditionType="StringEqualNocase" />
                        </Condition>
                      </Action>
                    </Actions>
                    <Condition Enabled="true" Grouping="Or">
                      <ConditionSingle Enabled="true" ExpressionL="${name}" ExpressionTypeL="String" ExpressionR="${_ffxivplayer}" ExpressionTypeR="String" ConditionType="StringEqualNocase" />
                    </Condition>
                  </Trigger>
                </Triggers>
              </Folder>
            </Folders>
            <Triggers>
              <Trigger Enabled="true" Name="技能判定" Id="d30f61d6-153b-4854-bea0-0ac5de805c75" RegularExpression="^.{14} 1[56]:.{8}:(?&lt;CasterName&gt;[^:]+?):(?&lt;AbilityID&gt;[^:]+?):(?&lt;AbilityName&gt;[^:]+?):(?&lt;Damage&gt;.+?):(?&lt;TargetName&gt;[^:]+?):" PeriodRefire="Deny" RefirePeriodExpression="100" Description="木人|伊甸|至尊伊甸|伊甸守护者|虚无行者|厄瑞玻斯的巨腕|利维亚桑|泰坦|极大泰坦|guardian of paradise|エデン?ガーデナー|Voidwalker|ヴォイドウォーカー|the Hand of Erebos|エレボスの巨腕|Leviathan|リヴァイアサン|Titan|タイタン|Titan Maximum|マキシタイタン">
                <Actions>
                  <Action OrderNumber="1" JsonEndpointExpression="http://127.0.0.1:${_env[PostNamazu]}/command" JsonPayloadExpression="/${func:tolower:${var:_AT_技能判定_发送频道}} ${CasterName} → ${AbilityName}    减伤:${var:减伤_鼓舞}${var:减伤_黑夜领域}${var:减伤_天星冲日（夜）}${var:减伤_炽天的幕帘}${var:减伤_雪仇_${CasterName}}${var:减伤_牵制_${CasterName}}${var:减伤_昏乱_${CasterName}}${var:减伤_策动}${var:减伤_防守之桑巴}${var:减伤_行吟}${var:减伤_节制}${var:减伤_命运之轮}${var:减伤_野战治疗阵}${var:减伤_异想的幻光}${var:减伤_圣光幕帘}${var:减伤_武装}${var:减伤_光之心}${var:减伤_摆脱}${var:减伤_暗黑布道}" TextAuraFontSize="9" TextAuraFontName="宋体" ActionType="GenericJson" Asynchronous="False">
                    <Condition Enabled="false" Grouping="And" />
                  </Action>
                </Actions>
                <Condition Enabled="true" Grouping="And">
                  <ConditionSingle Enabled="true" ExpressionL="${TargetName}" ExpressionTypeL="String" ExpressionR="${_ffxivplayer}" ExpressionTypeR="String" ConditionType="StringEqualNocase" />
                  <ConditionSingle Enabled="true" ExpressionL="AT_监控ID" ExpressionTypeL="String" ExpressionR="${AbilityID}" ExpressionTypeR="String" ConditionType="ListContains" />
                </Condition>
              </Trigger>
            </Triggers>
          </Folder>
          <Folder Id="e0e52132-82b7-4b61-bbd4-6ed3a4688fe9" Name="普攻非T玩家" Enabled="false">
            <Folders />
            <Triggers>
              <Trigger Enabled="true" Name="攻击判定" Id="d404f81e-bc8e-4468-86af-d9dfd07941f2" RegularExpression="^.{15}15:.{8}:(?&lt;BossName&gt;至尊伊甸|伊甸守护者|虚无行者|利维亚桑|泰坦|极大泰坦|拉姆|迦楼罗|伊弗利特|赤翼罗羯坨博叉|暗黑心象|希瓦|圣龙):.+?:(?&lt;AbilityName&gt;攻击|Unknown_(42D9|413D|3E60|367)):.{8}:(?&lt;TargetName&gt;[^:]+?):.+?:(?&lt;damage&gt;.+?):">
                <Actions>
                  <Action OrderNumber="1" JsonEndpointExpression="http://127.0.0.1:${_env[PostNamazu]}/command" JsonPayloadExpression="/${func:tolower:${var:_AT_伊甸平A职能_发送频道}} BOSS对 【${var:${TargetName}职业}】 的攻击造成了${numeric:hex2dec(${func:substring(0,4):${func:padleft(48,8):${damage}}})}点伤害！" TextAuraFontSize="9" TextAuraFontName="宋体" ActionType="GenericJson">
                    <Condition Enabled="true" Grouping="And">
                      <ConditionSingle Enabled="true" ExpressionL="${_ffxivparty[${TargetName}].role}" ExpressionTypeL="String" ExpressionR="Tank" ExpressionTypeR="String" ConditionType="StringNotEqualNocase" />
                      <ConditionSingle Enabled="true" ExpressionL="${func:substring(4,1):${func:padleft(48,8):${damage}}}" ExpressionTypeL="Numeric" ExpressionR="4" ExpressionTypeR="Numeric" ConditionType="StringNotEqualNocase" />
                    </Condition>
                  </Action>
                </Actions>
                <Condition Enabled="false" Grouping="And" />
              </Trigger>
            </Triggers>
          </Folder>
          <Folder Id="4c7c1d24-444c-4d23-a278-abd7790198a4" Name="死人发送即刻CD" Enabled="true">
            <Folders />
            <Triggers>
              <Trigger Enabled="true" Name="Swiftcast" Id="8ced9a7f-0b44-4524-b4b6-024dffd9cb69" RegularExpression="^.{14} 1A:.{8}:([^:]+?) gains the effect of (即刻咏唱|Swiftcast|迅速魔) ">
                <Actions>
                  <Action OrderNumber="1" LogLevel="-1" TableVariableOp="Set" TableVariableName="队伍监控_即刻" TableVariableExpression="${_systemtimems}" TableVariableX="2" TableVariableY="1" TextAuraFontSize="9" TextAuraFontName="宋体" ActionType="TableVariable">
                    <Condition Enabled="true" Grouping="Or">
                      <ConditionSingle Enabled="true" ExpressionL="${_ffxivparty[$1].job}" ExpressionTypeL="String" ExpressionR="WHM" ExpressionTypeR="String" ConditionType="StringEqualNocase" />
                    </Condition>
                  </Action>
                  <Action OrderNumber="2" LogLevel="-1" TableVariableOp="Set" TableVariableName="队伍监控_即刻" TableVariableExpression="${_systemtimems}" TableVariableX="2" TableVariableY="2" TextAuraFontSize="9" TextAuraFontName="宋体" ActionType="TableVariable">
                    <Condition Enabled="true" Grouping="Or">
                      <ConditionSingle Enabled="true" ExpressionL="${_ffxivparty[$1].job}" ExpressionTypeL="String" ExpressionR="AST" ExpressionTypeR="String" ConditionType="StringEqualNocase" />
                    </Condition>
                  </Action>
                  <Action OrderNumber="3" LogLevel="-1" TableVariableOp="Set" TableVariableName="队伍监控_即刻" TableVariableExpression="${_systemtimems}" TableVariableX="2" TableVariableY="3" TextAuraFontSize="9" TextAuraFontName="宋体" ActionType="TableVariable">
                    <Condition Enabled="true" Grouping="Or">
                      <ConditionSingle Enabled="true" ExpressionL="${_ffxivparty[$1].job}" ExpressionTypeL="String" ExpressionR="SCH" ExpressionTypeR="String" ConditionType="StringEqualNocase" />
                    </Condition>
                  </Action>
                  <Action OrderNumber="4" LogLevel="-1" TableVariableOp="Set" TableVariableName="队伍监控_即刻" TableVariableExpression="${_systemtimems}" TableVariableX="2" TableVariableY="4" TextAuraFontSize="9" TextAuraFontName="宋体" ActionType="TableVariable">
                    <Condition Enabled="true" Grouping="Or">
                      <ConditionSingle Enabled="true" ExpressionL="${_ffxivparty[$1].job}" ExpressionTypeL="String" ExpressionR="SMN" ExpressionTypeR="String" ConditionType="StringEqualNocase" />
                    </Condition>
                  </Action>
                </Actions>
                <Condition Enabled="true" Grouping="Or">
                  <ConditionSingle Enabled="true" ExpressionL="${_ffxivparty[$1].inparty}" ExpressionTypeL="Numeric" ExpressionR="1" ExpressionTypeR="Numeric" ConditionType="StringEqualNocase" />
                </Condition>
              </Trigger>
              <Trigger Enabled="true" Name="Reset" Id="0caa2d29-6cbf-4acd-b6f4-07e82f1e328e" RegularExpression="^.{14} 21:.{8}:400000(03|1[026]):">
                <Actions>
                  <Action OrderNumber="1" LogLevel="-1" TableVariableName="队伍监控_即刻" TableVariableX="3" TableVariableY="4" TextAuraFontSize="9" TextAuraFontName="宋体" ActionType="TableVariable" Asynchronous="False">
                    <Condition Enabled="false" Grouping="Or" />
                  </Action>
                  <Action OrderNumber="2" LogLevel="-1" TableVariableOp="Resize" TableVariableName="队伍监控_即刻" TableVariableX="3" TableVariableY="4" TextAuraFontSize="9" TextAuraFontName="宋体" ActionType="TableVariable" Asynchronous="False">
                    <Condition Enabled="false" Grouping="Or" />
                  </Action>
                  <Action OrderNumber="3" LogLevel="-1" TableVariableOp="Set" TableVariableName="队伍监控_即刻" TableVariableExpression="WHM" TableVariableX="1" TableVariableY="1" TextAuraFontSize="9" TextAuraFontName="宋体" ActionType="TableVariable">
                    <Condition Enabled="false" Grouping="Or" />
                  </Action>
                  <Action OrderNumber="4" LogLevel="-1" TableVariableOp="Set" TableVariableName="队伍监控_即刻" TableVariableExpression="AST" TableVariableX="1" TableVariableY="2" TextAuraFontSize="9" TextAuraFontName="宋体" ActionType="TableVariable">
                    <Condition Enabled="false" Grouping="Or" />
                  </Action>
                  <Action OrderNumber="5" LogLevel="-1" TableVariableOp="Set" TableVariableName="队伍监控_即刻" TableVariableExpression="SCH" TableVariableX="1" TableVariableY="3" TextAuraFontSize="9" TextAuraFontName="宋体" ActionType="TableVariable">
                    <Condition Enabled="false" Grouping="Or" />
                  </Action>
                  <Action OrderNumber="6" LogLevel="-1" TableVariableOp="Set" TableVariableName="队伍监控_即刻" TableVariableExpression="SMN" TableVariableX="1" TableVariableY="4" TextAuraFontSize="9" TextAuraFontName="宋体" ActionType="TableVariable">
                    <Condition Enabled="false" Grouping="Or" />
                  </Action>
                  <Action OrderNumber="7" LogLevel="-1" TableVariableOp="Set" TableVariableName="队伍监控_即刻" TableVariableExpression="0" TableVariableX="2" TableVariableY="1" TextAuraFontSize="9" TextAuraFontName="宋体" ActionType="TableVariable">
                    <Condition Enabled="false" Grouping="Or" />
                  </Action>
                  <Action OrderNumber="8" LogLevel="-1" TableVariableOp="Set" TableVariableName="队伍监控_即刻" TableVariableExpression="0" TableVariableX="2" TableVariableY="2" TextAuraFontSize="9" TextAuraFontName="宋体" ActionType="TableVariable">
                    <Condition Enabled="false" Grouping="Or" />
                  </Action>
                  <Action OrderNumber="9" LogLevel="-1" TableVariableOp="Set" TableVariableName="队伍监控_即刻" TableVariableExpression="0" TableVariableX="2" TableVariableY="3" TextAuraFontSize="9" TextAuraFontName="宋体" ActionType="TableVariable">
                    <Condition Enabled="false" Grouping="Or" />
                  </Action>
                  <Action OrderNumber="10" LogLevel="-1" TableVariableOp="Set" TableVariableName="队伍监控_即刻" TableVariableExpression="0" TableVariableX="2" TableVariableY="4" TextAuraFontSize="9" TextAuraFontName="宋体" ActionType="TableVariable">
                    <Condition Enabled="false" Grouping="Or" />
                  </Action>
                </Actions>
                <Condition Enabled="false" Grouping="Or" />
              </Trigger>
              <Trigger Enabled="true" Sequential="True" Name="Dead" Id="66518d85-5589-433e-a25d-1898d05c3e6e" RegularExpression="^.{14} 19:(.+?) was" PeriodRefire="Deny" RefirePeriodExpression="5000">
                <Actions>
                  <Action OrderNumber="1" LogLevel="-1" VariableOp="UnsetRegex" VariableName="^队伍监控_即刻temp." TextAuraFontSize="9" TextAuraFontName="宋体" ActionType="Variable" Asynchronous="False">
                    <Condition Enabled="true" Grouping="Or" />
                  </Action>
                  <Action OrderNumber="2" LogLevel="-1" VariableOp="SetString" VariableName="队伍监控_即刻temp1" VariableExpression="白:${numeric:60-max(min(round((${_systemtimems}-${tvar:队伍监控_即刻[2][1]})/1000),60),0)}" TextAuraFontSize="9" TextAuraFontName="宋体" ActionType="Variable" Asynchronous="False">
                    <Condition Enabled="true" Grouping="Or">
                      <ConditionGroup Enabled="true" Grouping="And">
                        <ConditionSingle Enabled="true" ExpressionL="${_ffxivparty[1].job}" ExpressionTypeL="String" ExpressionR="WHM" ExpressionTypeR="String" ConditionType="StringEqualNocase" />
                        <ConditionSingle Enabled="true" ExpressionL="${_ffxivparty[1].currenthp}" ExpressionTypeL="Numeric" ExpressionR="0" ExpressionTypeR="Numeric" ConditionType="NumericGreater" />
                      </ConditionGroup>
                      <ConditionGroup Enabled="true" Grouping="And">
                        <ConditionSingle Enabled="true" ExpressionL="${_ffxivparty[2].job}" ExpressionTypeL="String" ExpressionR="WHM" ExpressionTypeR="String" ConditionType="StringEqualNocase" />
                        <ConditionSingle Enabled="true" ExpressionL="${_ffxivparty[2].currenthp}" ExpressionTypeL="Numeric" ExpressionR="0" ExpressionTypeR="Numeric" ConditionType="NumericGreater" />
                      </ConditionGroup>
                      <ConditionGroup Enabled="true" Grouping="And">
                        <ConditionSingle Enabled="true" ExpressionL="${_ffxivparty[3].job}" ExpressionTypeL="String" ExpressionR="WHM" ExpressionTypeR="String" ConditionType="StringEqualNocase" />
                        <ConditionSingle Enabled="true" ExpressionL="${_ffxivparty[3].currenthp}" ExpressionTypeL="Numeric" ExpressionR="0" ExpressionTypeR="Numeric" ConditionType="NumericGreater" />
                      </ConditionGroup>
                      <ConditionGroup Enabled="true" Grouping="And">
                        <ConditionSingle Enabled="true" ExpressionL="${_ffxivparty[4].job}" ExpressionTypeL="String" ExpressionR="WHM" ExpressionTypeR="String" ConditionType="StringEqualNocase" />
                        <ConditionSingle Enabled="true" ExpressionL="${_ffxivparty[4].currenthp}" ExpressionTypeL="Numeric" ExpressionR="0" ExpressionTypeR="Numeric" ConditionType="NumericGreater" />
                      </ConditionGroup>
                      <ConditionGroup Enabled="true" Grouping="And">
                        <ConditionSingle Enabled="true" ExpressionL="${_ffxivparty[5].job}" ExpressionTypeL="String" ExpressionR="WHM" ExpressionTypeR="String" ConditionType="StringEqualNocase" />
                        <ConditionSingle Enabled="true" ExpressionL="${_ffxivparty[5].currenthp}" ExpressionTypeL="Numeric" ExpressionR="0" ExpressionTypeR="Numeric" ConditionType="NumericGreater" />
                      </ConditionGroup>
                      <ConditionGroup Enabled="true" Grouping="And">
                        <ConditionSingle Enabled="true" ExpressionL="${_ffxivparty[6].job}" ExpressionTypeL="String" ExpressionR="WHM" ExpressionTypeR="String" ConditionType="StringEqualNocase" />
                        <ConditionSingle Enabled="true" ExpressionL="${_ffxivparty[6].currenthp}" ExpressionTypeL="Numeric" ExpressionR="0" ExpressionTypeR="Numeric" ConditionType="NumericGreater" />
                      </ConditionGroup>
                      <ConditionGroup Enabled="true" Grouping="And">
                        <ConditionSingle Enabled="true" ExpressionL="${_ffxivparty[7].job}" ExpressionTypeL="String" ExpressionR="WHM" ExpressionTypeR="String" ConditionType="StringEqualNocase" />
                        <ConditionSingle Enabled="true" ExpressionL="${_ffxivparty[7].currenthp}" ExpressionTypeL="Numeric" ExpressionR="0" ExpressionTypeR="Numeric" ConditionType="NumericGreater" />
                      </ConditionGroup>
                      <ConditionGroup Enabled="true" Grouping="And">
                        <ConditionSingle Enabled="true" ExpressionL="${_ffxivparty[8].job}" ExpressionTypeL="String" ExpressionR="WHM" ExpressionTypeR="String" ConditionType="StringEqualNocase" />
                        <ConditionSingle Enabled="true" ExpressionL="${_ffxivparty[8].currenthp}" ExpressionTypeL="Numeric" ExpressionR="0" ExpressionTypeR="Numeric" ConditionType="NumericGreater" />
                      </ConditionGroup>
                    </Condition>
                  </Action>
                  <Action OrderNumber="3" LogLevel="-1" VariableOp="SetString" VariableName="队伍监控_即刻temp2" VariableExpression="占:${numeric:60-max(min(round((${_systemtimems}-${tvar:队伍监控_即刻[2][2]})/1000),60),0)}" TextAuraFontSize="9" TextAuraFontName="宋体" ActionType="Variable" Asynchronous="False">
                    <Condition Enabled="true" Grouping="Or">
                      <ConditionGroup Enabled="true" Grouping="And">
                        <ConditionSingle Enabled="true" ExpressionL="${_ffxivparty[1].job}" ExpressionTypeL="String" ExpressionR="AST" ExpressionTypeR="String" ConditionType="StringEqualNocase" />
                        <ConditionSingle Enabled="true" ExpressionL="${_ffxivparty[1].currenthp}" ExpressionTypeL="Numeric" ExpressionR="0" ExpressionTypeR="Numeric" ConditionType="NumericGreater" />
                      </ConditionGroup>
                      <ConditionGroup Enabled="true" Grouping="And">
                        <ConditionSingle Enabled="true" ExpressionL="${_ffxivparty[2].job}" ExpressionTypeL="String" ExpressionR="AST" ExpressionTypeR="String" ConditionType="StringEqualNocase" />
                        <ConditionSingle Enabled="true" ExpressionL="${_ffxivparty[2].currenthp}" ExpressionTypeL="Numeric" ExpressionR="0" ExpressionTypeR="Numeric" ConditionType="NumericGreater" />
                      </ConditionGroup>
                      <ConditionGroup Enabled="true" Grouping="And">
                        <ConditionSingle Enabled="true" ExpressionL="${_ffxivparty[3].job}" ExpressionTypeL="String" ExpressionR="AST" ExpressionTypeR="String" ConditionType="StringEqualNocase" />
                        <ConditionSingle Enabled="true" ExpressionL="${_ffxivparty[3].currenthp}" ExpressionTypeL="Numeric" ExpressionR="0" ExpressionTypeR="Numeric" ConditionType="NumericGreater" />
                      </ConditionGroup>
                      <ConditionGroup Enabled="true" Grouping="And">
                        <ConditionSingle Enabled="true" ExpressionL="${_ffxivparty[4].job}" ExpressionTypeL="String" ExpressionR="AST" ExpressionTypeR="String" ConditionType="StringEqualNocase" />
                        <ConditionSingle Enabled="true" ExpressionL="${_ffxivparty[4].currenthp}" ExpressionTypeL="Numeric" ExpressionR="0" ExpressionTypeR="Numeric" ConditionType="NumericGreater" />
                      </ConditionGroup>
                      <ConditionGroup Enabled="true" Grouping="And">
                        <ConditionSingle Enabled="true" ExpressionL="${_ffxivparty[5].job}" ExpressionTypeL="String" ExpressionR="AST" ExpressionTypeR="String" ConditionType="StringEqualNocase" />
                        <ConditionSingle Enabled="true" ExpressionL="${_ffxivparty[5].currenthp}" ExpressionTypeL="Numeric" ExpressionR="0" ExpressionTypeR="Numeric" ConditionType="NumericGreater" />
                      </ConditionGroup>
                      <ConditionGroup Enabled="true" Grouping="And">
                        <ConditionSingle Enabled="true" ExpressionL="${_ffxivparty[6].job}" ExpressionTypeL="String" ExpressionR="AST" ExpressionTypeR="String" ConditionType="StringEqualNocase" />
                        <ConditionSingle Enabled="true" ExpressionL="${_ffxivparty[6].currenthp}" ExpressionTypeL="Numeric" ExpressionR="0" ExpressionTypeR="Numeric" ConditionType="NumericGreater" />
                      </ConditionGroup>
                      <ConditionGroup Enabled="true" Grouping="And">
                        <ConditionSingle Enabled="true" ExpressionL="${_ffxivparty[7].job}" ExpressionTypeL="String" ExpressionR="AST" ExpressionTypeR="String" ConditionType="StringEqualNocase" />
                        <ConditionSingle Enabled="true" ExpressionL="${_ffxivparty[7].currenthp}" ExpressionTypeL="Numeric" ExpressionR="0" ExpressionTypeR="Numeric" ConditionType="NumericGreater" />
                      </ConditionGroup>
                      <ConditionGroup Enabled="true" Grouping="And">
                        <ConditionSingle Enabled="true" ExpressionL="${_ffxivparty[8].job}" ExpressionTypeL="String" ExpressionR="AST" ExpressionTypeR="String" ConditionType="StringEqualNocase" />
                        <ConditionSingle Enabled="true" ExpressionL="${_ffxivparty[8].currenthp}" ExpressionTypeL="Numeric" ExpressionR="0" ExpressionTypeR="Numeric" ConditionType="NumericGreater" />
                      </ConditionGroup>
                    </Condition>
                  </Action>
                  <Action OrderNumber="4" LogLevel="-1" VariableOp="SetString" VariableName="队伍监控_即刻temp3" VariableExpression="学:${numeric:60-max(min(round((${_systemtimems}-${tvar:队伍监控_即刻[2][3]})/1000),60),0)}" TextAuraFontSize="9" TextAuraFontName="宋体" ActionType="Variable" Asynchronous="False">
                    <Condition Enabled="true" Grouping="Or">
                      <ConditionGroup Enabled="true" Grouping="And">
                        <ConditionSingle Enabled="true" ExpressionL="${_ffxivparty[1].job}" ExpressionTypeL="String" ExpressionR="SCH" ExpressionTypeR="String" ConditionType="StringEqualNocase" />
                        <ConditionSingle Enabled="true" ExpressionL="${_ffxivparty[1].currenthp}" ExpressionTypeL="Numeric" ExpressionR="0" ExpressionTypeR="Numeric" ConditionType="NumericGreater" />
                      </ConditionGroup>
                      <ConditionGroup Enabled="true" Grouping="And">
                        <ConditionSingle Enabled="true" ExpressionL="${_ffxivparty[2].job}" ExpressionTypeL="String" ExpressionR="SCH" ExpressionTypeR="String" ConditionType="StringEqualNocase" />
                        <ConditionSingle Enabled="true" ExpressionL="${_ffxivparty[2].currenthp}" ExpressionTypeL="Numeric" ExpressionR="0" ExpressionTypeR="Numeric" ConditionType="NumericGreater" />
                      </ConditionGroup>
                      <ConditionGroup Enabled="true" Grouping="And">
                        <ConditionSingle Enabled="true" ExpressionL="${_ffxivparty[3].job}" ExpressionTypeL="String" ExpressionR="SCH" ExpressionTypeR="String" ConditionType="StringEqualNocase" />
                        <ConditionSingle Enabled="true" ExpressionL="${_ffxivparty[3].currenthp}" ExpressionTypeL="Numeric" ExpressionR="0" ExpressionTypeR="Numeric" ConditionType="NumericGreater" />
                      </ConditionGroup>
                      <ConditionGroup Enabled="true" Grouping="And">
                        <ConditionSingle Enabled="true" ExpressionL="${_ffxivparty[4].job}" ExpressionTypeL="String" ExpressionR="SCH" ExpressionTypeR="String" ConditionType="StringEqualNocase" />
                        <ConditionSingle Enabled="true" ExpressionL="${_ffxivparty[4].currenthp}" ExpressionTypeL="Numeric" ExpressionR="0" ExpressionTypeR="Numeric" ConditionType="NumericGreater" />
                      </ConditionGroup>
                      <ConditionGroup Enabled="true" Grouping="And">
                        <ConditionSingle Enabled="true" ExpressionL="${_ffxivparty[5].job}" ExpressionTypeL="String" ExpressionR="SCH" ExpressionTypeR="String" ConditionType="StringEqualNocase" />
                        <ConditionSingle Enabled="true" ExpressionL="${_ffxivparty[5].currenthp}" ExpressionTypeL="Numeric" ExpressionR="0" ExpressionTypeR="Numeric" ConditionType="NumericGreater" />
                      </ConditionGroup>
                      <ConditionGroup Enabled="true" Grouping="And">
                        <ConditionSingle Enabled="true" ExpressionL="${_ffxivparty[6].job}" ExpressionTypeL="String" ExpressionR="SCH" ExpressionTypeR="String" ConditionType="StringEqualNocase" />
                        <ConditionSingle Enabled="true" ExpressionL="${_ffxivparty[6].currenthp}" ExpressionTypeL="Numeric" ExpressionR="0" ExpressionTypeR="Numeric" ConditionType="NumericGreater" />
                      </ConditionGroup>
                      <ConditionGroup Enabled="true" Grouping="And">
                        <ConditionSingle Enabled="true" ExpressionL="${_ffxivparty[7].job}" ExpressionTypeL="String" ExpressionR="SCH" ExpressionTypeR="String" ConditionType="StringEqualNocase" />
                        <ConditionSingle Enabled="true" ExpressionL="${_ffxivparty[7].currenthp}" ExpressionTypeL="Numeric" ExpressionR="0" ExpressionTypeR="Numeric" ConditionType="NumericGreater" />
                      </ConditionGroup>
                      <ConditionGroup Enabled="true" Grouping="And">
                        <ConditionSingle Enabled="true" ExpressionL="${_ffxivparty[8].job}" ExpressionTypeL="String" ExpressionR="SCH" ExpressionTypeR="String" ConditionType="StringEqualNocase" />
                        <ConditionSingle Enabled="true" ExpressionL="${_ffxivparty[8].currenthp}" ExpressionTypeL="Numeric" ExpressionR="0" ExpressionTypeR="Numeric" ConditionType="NumericGreater" />
                      </ConditionGroup>
                    </Condition>
                  </Action>
                  <Action OrderNumber="5" LogLevel="-1" VariableOp="SetString" VariableName="队伍监控_即刻temp4" VariableExpression="召:${numeric:60-max(min(round((${_systemtimems}-${tvar:队伍监控_即刻[2][4]})/1000),60),0)}" TextAuraFontSize="9" TextAuraFontName="宋体" ActionType="Variable" Asynchronous="False">
                    <Condition Enabled="true" Grouping="Or">
                      <ConditionGroup Enabled="true" Grouping="And">
                        <ConditionSingle Enabled="true" ExpressionL="${_ffxivparty[1].job}" ExpressionTypeL="String" ExpressionR="SMN" ExpressionTypeR="String" ConditionType="StringEqualNocase" />
                        <ConditionSingle Enabled="true" ExpressionL="${_ffxivparty[1].currenthp}" ExpressionTypeL="Numeric" ExpressionR="0" ExpressionTypeR="Numeric" ConditionType="NumericGreater" />
                      </ConditionGroup>
                      <ConditionGroup Enabled="true" Grouping="And">
                        <ConditionSingle Enabled="true" ExpressionL="${_ffxivparty[2].job}" ExpressionTypeL="String" ExpressionR="SMN" ExpressionTypeR="String" ConditionType="StringEqualNocase" />
                        <ConditionSingle Enabled="true" ExpressionL="${_ffxivparty[2].currenthp}" ExpressionTypeL="Numeric" ExpressionR="0" ExpressionTypeR="Numeric" ConditionType="NumericGreater" />
                      </ConditionGroup>
                      <ConditionGroup Enabled="true" Grouping="And">
                        <ConditionSingle Enabled="true" ExpressionL="${_ffxivparty[3].job}" ExpressionTypeL="String" ExpressionR="SMN" ExpressionTypeR="String" ConditionType="StringEqualNocase" />
                        <ConditionSingle Enabled="true" ExpressionL="${_ffxivparty[3].currenthp}" ExpressionTypeL="Numeric" ExpressionR="0" ExpressionTypeR="Numeric" ConditionType="NumericGreater" />
                      </ConditionGroup>
                      <ConditionGroup Enabled="true" Grouping="And">
                        <ConditionSingle Enabled="true" ExpressionL="${_ffxivparty[4].job}" ExpressionTypeL="String" ExpressionR="SMN" ExpressionTypeR="String" ConditionType="StringEqualNocase" />
                        <ConditionSingle Enabled="true" ExpressionL="${_ffxivparty[4].currenthp}" ExpressionTypeL="Numeric" ExpressionR="0" ExpressionTypeR="Numeric" ConditionType="NumericGreater" />
                      </ConditionGroup>
                      <ConditionGroup Enabled="true" Grouping="And">
                        <ConditionSingle Enabled="true" ExpressionL="${_ffxivparty[5].job}" ExpressionTypeL="String" ExpressionR="SMN" ExpressionTypeR="String" ConditionType="StringEqualNocase" />
                        <ConditionSingle Enabled="true" ExpressionL="${_ffxivparty[5].currenthp}" ExpressionTypeL="Numeric" ExpressionR="0" ExpressionTypeR="Numeric" ConditionType="NumericGreater" />
                      </ConditionGroup>
                      <ConditionGroup Enabled="true" Grouping="And">
                        <ConditionSingle Enabled="true" ExpressionL="${_ffxivparty[6].job}" ExpressionTypeL="String" ExpressionR="SMN" ExpressionTypeR="String" ConditionType="StringEqualNocase" />
                        <ConditionSingle Enabled="true" ExpressionL="${_ffxivparty[6].currenthp}" ExpressionTypeL="Numeric" ExpressionR="0" ExpressionTypeR="Numeric" ConditionType="NumericGreater" />
                      </ConditionGroup>
                      <ConditionGroup Enabled="true" Grouping="And">
                        <ConditionSingle Enabled="true" ExpressionL="${_ffxivparty[7].job}" ExpressionTypeL="String" ExpressionR="SMN" ExpressionTypeR="String" ConditionType="StringEqualNocase" />
                        <ConditionSingle Enabled="true" ExpressionL="${_ffxivparty[7].currenthp}" ExpressionTypeL="Numeric" ExpressionR="0" ExpressionTypeR="Numeric" ConditionType="NumericGreater" />
                      </ConditionGroup>
                      <ConditionGroup Enabled="true" Grouping="And">
                        <ConditionSingle Enabled="true" ExpressionL="${_ffxivparty[8].job}" ExpressionTypeL="String" ExpressionR="SMN" ExpressionTypeR="String" ConditionType="StringEqualNocase" />
                        <ConditionSingle Enabled="true" ExpressionL="${_ffxivparty[8].currenthp}" ExpressionTypeL="Numeric" ExpressionR="0" ExpressionTypeR="Numeric" ConditionType="NumericGreater" />
                      </ConditionGroup>
                    </Condition>
                  </Action>
                  <Action OrderNumber="6" JsonEndpointExpression="http://127.0.0.1:${_env[PostNamazu]}/command" JsonPayloadExpression="/${func:tolower:${var:_AT_即刻_发送频道}} 即刻CD：${var:队伍监控_即刻temp1}${var:队伍监控_即刻temp2}${var:队伍监控_即刻temp3}${var:队伍监控_即刻temp4}" LogLevel="-1" TextAuraFontSize="9" TextAuraFontName="宋体" ActionType="GenericJson" Asynchronous="False">
                    <Condition Enabled="true" Grouping="Or">
                      <ConditionSingle Enabled="true" ExpressionL="${evar:队伍监控_即刻temp3}" ExpressionTypeL="Numeric" ExpressionR="1" ExpressionTypeR="Numeric" ConditionType="NumericEqual" />
                      <ConditionSingle Enabled="true" ExpressionL="${evar:队伍监控_即刻temp1}" ExpressionTypeL="Numeric" ExpressionR="1" ExpressionTypeR="Numeric" ConditionType="NumericEqual" />
                      <ConditionSingle Enabled="true" ExpressionL="${evar:队伍监控_即刻temp2}" ExpressionTypeL="Numeric" ExpressionR="1" ExpressionTypeR="Numeric" ConditionType="NumericEqual" />
                      <ConditionSingle Enabled="true" ExpressionL="${evar:队伍监控_即刻temp4}" ExpressionTypeL="Numeric" ExpressionR="1" ExpressionTypeR="Numeric" ConditionType="NumericEqual" />
                    </Condition>
                  </Action>
                </Actions>
                <Condition Enabled="true" Grouping="Or">
                  <ConditionSingle Enabled="true" ExpressionL="${_ffxivparty[$1].inparty}" ExpressionTypeL="Numeric" ExpressionR="1" ExpressionTypeR="Numeric" ConditionType="StringEqualNocase" />
                </Condition>
              </Trigger>
            </Triggers>
          </Folder>
          <Folder Id="7b6b0d76-55a2-47f2-a8c4-27adbd8feb33" Name="获取职业" Enabled="true">
            <Folders />
            <Triggers>
              <Trigger Enabled="true" Sequential="True" Name="长" Id="00501ec3-caee-411b-aee5-db4eb76af3a9" RegularExpression="^.{15}00:0038:获取职业（长）$">
                <Actions>
                  <Action OrderNumber="1" VariableOp="SetNumeric" VariableName="Souma_Get_Team_Role_Reset" VariableExpression="0" TextAuraFontSize="9" TextAuraFontName="宋体" ActionType="Variable" Asynchronous="False">
                    <Condition Enabled="true" Grouping="Or">
                      <ConditionSingle Enabled="true" ExpressionL="${evar:Souma_Get_Team_Role_Reset}" ExpressionTypeL="Numeric" ExpressionR="1" ExpressionTypeR="Numeric" ConditionType="NumericNotEqual" />
                      <ConditionSingle Enabled="true" ExpressionL="${var:Souma_Get_Team_Role_Reset}" ExpressionTypeL="Numeric" ExpressionR="8" ExpressionTypeR="Numeric" ConditionType="NumericEqual" />
                    </Condition>
                  </Action>
                  <Action OrderNumber="2" VariableOp="SetNumeric" VariableName="Souma_Get_Team_Role_Reset" VariableExpression="${var:Souma_Get_Team_Role_Reset}+1" TextAuraFontSize="9" TextAuraFontName="宋体" ActionType="Variable" Asynchronous="False">
                    <Condition Enabled="true" Grouping="Or">
                      <ConditionSingle Enabled="true" ExpressionL="${evar:Souma_Get_Team_Role_Reset}" ExpressionTypeL="Numeric" ExpressionR="1" ExpressionTypeR="Numeric" ConditionType="NumericEqual" />
                    </Condition>
                  </Action>
                  <Action OrderNumber="3" VariableOp="SetString" VariableName="${_ffxivparty[${var:Souma_Get_Team_Role_Reset}].name}职业" VariableExpression="骑士" TextAuraFontSize="9" TextAuraFontName="宋体" ActionType="Variable" Asynchronous="False">
                    <Condition Enabled="true" Grouping="Or">
                      <ConditionSingle Enabled="true" ExpressionL="${_ffxivparty[${var:Souma_Get_Team_Role_Reset}].job}" ExpressionTypeL="String" ExpressionR="PLD" ExpressionTypeR="String" ConditionType="StringEqualNocase" />
                    </Condition>
                  </Action>
                  <Action OrderNumber="4" VariableOp="SetString" VariableName="${_ffxivparty[${var:Souma_Get_Team_Role_Reset}].name}职业" VariableExpression="战士" TextAuraFontSize="9" TextAuraFontName="宋体" ActionType="Variable" Asynchronous="False">
                    <Condition Enabled="true" Grouping="Or">
                      <ConditionSingle Enabled="true" ExpressionL="${_ffxivparty[${var:Souma_Get_Team_Role_Reset}].job}" ExpressionTypeL="String" ExpressionR="WAR" ExpressionTypeR="String" ConditionType="StringEqualNocase" />
                    </Condition>
                  </Action>
                  <Action OrderNumber="5" VariableOp="SetString" VariableName="${_ffxivparty[${var:Souma_Get_Team_Role_Reset}].name}职业" VariableExpression="暗骑" TextAuraFontSize="9" TextAuraFontName="宋体" ActionType="Variable" Asynchronous="False">
                    <Condition Enabled="true" Grouping="Or">
                      <ConditionSingle Enabled="true" ExpressionL="${_ffxivparty[${var:Souma_Get_Team_Role_Reset}].job}" ExpressionTypeL="String" ExpressionR="DRK" ExpressionTypeR="String" ConditionType="StringEqualNocase" />
                    </Condition>
                  </Action>
                  <Action OrderNumber="6" VariableOp="SetString" VariableName="${_ffxivparty[${var:Souma_Get_Team_Role_Reset}].name}职业" VariableExpression="枪刃" TextAuraFontSize="9" TextAuraFontName="宋体" ActionType="Variable" Asynchronous="False">
                    <Condition Enabled="true" Grouping="Or">
                      <ConditionSingle Enabled="true" ExpressionL="${_ffxivparty[${var:Souma_Get_Team_Role_Reset}].job}" ExpressionTypeL="String" ExpressionR="GNB" ExpressionTypeR="String" ConditionType="StringEqualNocase" />
                    </Condition>
                  </Action>
                  <Action OrderNumber="7" VariableOp="SetString" VariableName="${_ffxivparty[${var:Souma_Get_Team_Role_Reset}].name}职业" VariableExpression="白魔" TextAuraFontSize="9" TextAuraFontName="宋体" ActionType="Variable" Asynchronous="False">
                    <Condition Enabled="true" Grouping="Or">
                      <ConditionSingle Enabled="true" ExpressionL="${_ffxivparty[${var:Souma_Get_Team_Role_Reset}].job}" ExpressionTypeL="String" ExpressionR="WHM" ExpressionTypeR="String" ConditionType="StringEqualNocase" />
                    </Condition>
                  </Action>
                  <Action OrderNumber="8" VariableOp="SetString" VariableName="${_ffxivparty[${var:Souma_Get_Team_Role_Reset}].name}职业" VariableExpression="学者" TextAuraFontSize="9" TextAuraFontName="宋体" ActionType="Variable" Asynchronous="False">
                    <Condition Enabled="true" Grouping="Or">
                      <ConditionSingle Enabled="true" ExpressionL="${_ffxivparty[${var:Souma_Get_Team_Role_Reset}].job}" ExpressionTypeL="String" ExpressionR="SCH" ExpressionTypeR="String" ConditionType="StringEqualNocase" />
                    </Condition>
                  </Action>
                  <Action OrderNumber="9" VariableOp="SetString" VariableName="${_ffxivparty[${var:Souma_Get_Team_Role_Reset}].name}职业" VariableExpression="占星" TextAuraFontSize="9" TextAuraFontName="宋体" ActionType="Variable" Asynchronous="False">
                    <Condition Enabled="true" Grouping="Or">
                      <ConditionSingle Enabled="true" ExpressionL="${_ffxivparty[${var:Souma_Get_Team_Role_Reset}].job}" ExpressionTypeL="String" ExpressionR="AST" ExpressionTypeR="String" ConditionType="StringEqualNocase" />
                    </Condition>
                  </Action>
                  <Action OrderNumber="10" VariableOp="SetString" VariableName="${_ffxivparty[${var:Souma_Get_Team_Role_Reset}].name}职业" VariableExpression="武僧" TextAuraFontSize="9" TextAuraFontName="宋体" ActionType="Variable" Asynchronous="False">
                    <Condition Enabled="true" Grouping="Or">
                      <ConditionSingle Enabled="true" ExpressionL="${_ffxivparty[${var:Souma_Get_Team_Role_Reset}].job}" ExpressionTypeL="String" ExpressionR="MNK" ExpressionTypeR="String" ConditionType="StringEqualNocase" />
                    </Condition>
                  </Action>
                  <Action OrderNumber="11" VariableOp="SetString" VariableName="${_ffxivparty[${var:Souma_Get_Team_Role_Reset}].name}职业" VariableExpression="龙骑" TextAuraFontSize="9" TextAuraFontName="宋体" ActionType="Variable" Asynchronous="False">
                    <Condition Enabled="true" Grouping="Or">
                      <ConditionSingle Enabled="true" ExpressionL="${_ffxivparty[${var:Souma_Get_Team_Role_Reset}].job}" ExpressionTypeL="String" ExpressionR="DRG" ExpressionTypeR="String" ConditionType="StringEqualNocase" />
                    </Condition>
                  </Action>
                  <Action OrderNumber="12" VariableOp="SetString" VariableName="${_ffxivparty[${var:Souma_Get_Team_Role_Reset}].name}职业" VariableExpression="忍者" TextAuraFontSize="9" TextAuraFontName="宋体" ActionType="Variable" Asynchronous="False">
                    <Condition Enabled="true" Grouping="Or">
                      <ConditionSingle Enabled="true" ExpressionL="${_ffxivparty[${var:Souma_Get_Team_Role_Reset}].job}" ExpressionTypeL="String" ExpressionR="NIN" ExpressionTypeR="String" ConditionType="StringEqualNocase" />
                    </Condition>
                  </Action>
                  <Action OrderNumber="13" VariableOp="SetString" VariableName="${_ffxivparty[${var:Souma_Get_Team_Role_Reset}].name}职业" VariableExpression="武士" TextAuraFontSize="9" TextAuraFontName="宋体" ActionType="Variable" Asynchronous="False">
                    <Condition Enabled="true" Grouping="Or">
                      <ConditionSingle Enabled="true" ExpressionL="${_ffxivparty[${var:Souma_Get_Team_Role_Reset}].job}" ExpressionTypeL="String" ExpressionR="SAM" ExpressionTypeR="String" ConditionType="StringEqualNocase" />
                    </Condition>
                  </Action>
                  <Action OrderNumber="14" VariableOp="SetString" VariableName="${_ffxivparty[${var:Souma_Get_Team_Role_Reset}].name}职业" VariableExpression="诗人" TextAuraFontSize="9" TextAuraFontName="宋体" ActionType="Variable" Asynchronous="False">
                    <Condition Enabled="true" Grouping="Or">
                      <ConditionSingle Enabled="true" ExpressionL="${_ffxivparty[${var:Souma_Get_Team_Role_Reset}].job}" ExpressionTypeL="String" ExpressionR="BRD" ExpressionTypeR="String" ConditionType="StringEqualNocase" />
                    </Condition>
                  </Action>
                  <Action OrderNumber="15" VariableOp="SetString" VariableName="${_ffxivparty[${var:Souma_Get_Team_Role_Reset}].name}职业" VariableExpression="机工" TextAuraFontSize="9" TextAuraFontName="宋体" ActionType="Variable" Asynchronous="False">
                    <Condition Enabled="true" Grouping="Or">
                      <ConditionSingle Enabled="true" ExpressionL="${_ffxivparty[${var:Souma_Get_Team_Role_Reset}].job}" ExpressionTypeL="String" ExpressionR="MCH" ExpressionTypeR="String" ConditionType="StringEqualNocase" />
                    </Condition>
                  </Action>
                  <Action OrderNumber="16" VariableOp="SetString" VariableName="${_ffxivparty[${var:Souma_Get_Team_Role_Reset}].name}职业" VariableExpression="舞者" TextAuraFontSize="9" TextAuraFontName="宋体" ActionType="Variable" Asynchronous="False">
                    <Condition Enabled="true" Grouping="Or">
                      <ConditionSingle Enabled="true" ExpressionL="${_ffxivparty[${var:Souma_Get_Team_Role_Reset}].job}" ExpressionTypeL="String" ExpressionR="DNC" ExpressionTypeR="String" ConditionType="StringEqualNocase" />
                    </Condition>
                  </Action>
                  <Action OrderNumber="17" VariableOp="SetString" VariableName="${_ffxivparty[${var:Souma_Get_Team_Role_Reset}].name}职业" VariableExpression="黑魔" TextAuraFontSize="9" TextAuraFontName="宋体" ActionType="Variable" Asynchronous="False">
                    <Condition Enabled="true" Grouping="Or">
                      <ConditionSingle Enabled="true" ExpressionL="${_ffxivparty[${var:Souma_Get_Team_Role_Reset}].job}" ExpressionTypeL="String" ExpressionR="BLM" ExpressionTypeR="String" ConditionType="StringEqualNocase" />
                    </Condition>
                  </Action>
                  <Action OrderNumber="18" VariableOp="SetString" VariableName="${_ffxivparty[${var:Souma_Get_Team_Role_Reset}].name}职业" VariableExpression="召唤" TextAuraFontSize="9" TextAuraFontName="宋体" ActionType="Variable" Asynchronous="False">
                    <Condition Enabled="true" Grouping="Or">
                      <ConditionSingle Enabled="true" ExpressionL="${_ffxivparty[${var:Souma_Get_Team_Role_Reset}].job}" ExpressionTypeL="String" ExpressionR="SMN" ExpressionTypeR="String" ConditionType="StringEqualNocase" />
                    </Condition>
                  </Action>
                  <Action OrderNumber="19" VariableOp="SetString" VariableName="${_ffxivparty[${var:Souma_Get_Team_Role_Reset}].name}职业" VariableExpression="赤魔" TextAuraFontSize="9" TextAuraFontName="宋体" ActionType="Variable" Asynchronous="False">
                    <Condition Enabled="true" Grouping="Or">
                      <ConditionSingle Enabled="true" ExpressionL="${_ffxivparty[${var:Souma_Get_Team_Role_Reset}].job}" ExpressionTypeL="String" ExpressionR="RDM" ExpressionTypeR="String" ConditionType="StringEqualNocase" />
                    </Condition>
                  </Action>
                  <Action OrderNumber="20" TextAuraFontSize="9" TextAuraFontName="宋体" TriggerId="00501ec3-caee-411b-aee5-db4eb76af3a9" TriggerText="[00:00:00.000] 00:0038:获取职业（长）" ActionType="Trigger" ExecutionDelayExpression="1" Asynchronous="False">
                    <Condition Enabled="true" Grouping="And">
                      <ConditionSingle Enabled="true" ExpressionL="${var:Souma_Get_Team_Role_Reset}" ExpressionTypeL="Numeric" ExpressionR="1" ExpressionTypeR="Numeric" ConditionType="NumericGreaterEqual" />
                      <ConditionSingle Enabled="true" ExpressionL="${var:Souma_Get_Team_Role_Reset}" ExpressionTypeL="Numeric" ExpressionR="8" ExpressionTypeR="Numeric" ConditionType="NumericLess" />
                    </Condition>
                  </Action>
                </Actions>
                <Condition Enabled="false" Grouping="Or" />
              </Trigger>
              <Trigger Enabled="true" Name="触发" Id="6b3f7594-5284-4332-9372-51fa9e945791" RegularExpression="^.{14} 0B:|^.{14} 21:.{8}:400000(03|1[026]):" PrevActions="Interrupt" Scheduling="FromRefirePeriod" PeriodRefire="Deny" RefirePeriodExpression="20000">
                <Actions>
                  <Action OrderNumber="1" VariableOp="UnsetRegex" VariableName=".*职业" VariableExpression="true" TextAuraFontSize="9" TextAuraFontName="宋体" ActionType="Variable" ExecutionDelayExpression="1" Asynchronous="False">
                    <Condition Enabled="false" Grouping="Or" />
                  </Action>
                  <Action OrderNumber="2" VariableName="Souma_Get_Team_Role_Reset" VariableExpression="0" TextAuraFontSize="9" TextAuraFontName="宋体" ActionType="Variable" ExecutionDelayExpression="1" Asynchronous="False">
                    <Condition Enabled="false" Grouping="Or" />
                  </Action>
                  <Action OrderNumber="3" TextAuraFontSize="9" TextAuraFontName="宋体" TriggerId="00501ec3-caee-411b-aee5-db4eb76af3a9" TriggerText="[00:00:00.000] 00:0038:获取职业（长）" ActionType="Trigger" ExecutionDelayExpression="1000" Asynchronous="False">
                    <Condition Enabled="false" Grouping="Or" />
                  </Action>
                  <Action OrderNumber="4" UseTTSTextExpression="${var:${_ffxivplayer}职业}" TextAuraFontSize="9" TextAuraFontName="宋体" Enabled="False" ActionType="UseTTS" ExecutionDelayExpression="50" Asynchronous="False">
                    <Condition Enabled="false" Grouping="Or" />
                  </Action>
                </Actions>
                <Condition Enabled="false" Grouping="Or" />
              </Trigger>
            </Triggers>
          </Folder>
        </Folders>
        <Triggers />
      </Folder>
    </Folders>
    <Triggers>
      <Trigger Enabled="false" IsReadme="True" Name="使用说明（双击打开描述）" Id="b284c88d-99cf-4970-88fd-9501fcb7e1ff" RegularExpression="" Description="1.开启依赖：[鲶鱼精邮差]&#xD;&#xA;&#xD;&#xA;2.配置鲶鱼精邮差的端口环境(bat)。重启ACT&#xD;&#xA;&#xD;&#xA;3.可在[*设置]中设置发送的聊天频道">
        <Actions />
        <Condition Enabled="false" Grouping="Or" />
      </Trigger>
    </Triggers>
  </ExportedFolder>
</TriggernometryExport>